flask_marshmallow/__init__.py
flask_marshmallow/compat.py
flask_marshmallow/fields.py
flask_marshmallow/schema.py
flask_marshmallow/sqla.py
flask_marshmallow-0.15.0.dist-info/LICENSE
flask_marshmallow-0.15.0.dist-info/METADATA
flask_marshmallow-0.15.0.dist-info/WHEEL
flask_marshmallow-0.15.0.dist-info/top_level.txt
flask_marshmallow-0.15.0.dist-info/RECORD
