Metadata-Version: 2.1
Name: flask-marshmallow
Version: 0.15.0
Summary: Flask + marshmallow for beautiful APIs
Home-page: https://github.com/marshmallow-code/flask-marshmallow
Author: Steven Loria
Author-email: sloria1@gmail.com
License: MIT
Project-URL: Issues, https://github.com/marshmallow-code/flask-marshmallow/issues
Project-URL: Funding, https://opencollective.com/marshmallow
Keywords: flask-marshmallow
Classifier: Development Status :: 4 - Beta
Classifier: Environment :: Web Environment
Classifier: Intended Audience :: Developers
Classifier: License :: OSI Approved :: MIT License
Classifier: Natural Language :: English
Classifier: Programming Language :: Python :: 3
Classifier: Programming Language :: Python :: 3.7
Classifier: Programming Language :: Python :: 3.8
Classifier: Programming Language :: Python :: 3.9
Classifier: Programming Language :: Python :: 3.10
Classifier: Programming Language :: Python :: 3.11
Classifier: Topic :: Internet :: WWW/HTTP :: Dynamic Content
Requires-Python: >=3.7
Provides-Extra: sqlalchemy
Provides-Extra: docs
Provides-Extra: tests
Provides-Extra: dev
License-File: LICENSE
